README.md
setup.py
web3mq/__init__.py
web3mq/client.py
web3mq/contact.py
web3mq/exception.py
web3mq/message.py
web3mq/room.py
web3mq/singleton_utils.py
web3mq/sync_request.py
web3mq/user.py
web3mq/version.py
web3mq.egg-info/PKG-INFO
web3mq.egg-info/SOURCES.txt
web3mq.egg-info/dependency_links.txt
web3mq.egg-info/not-zip-safe
web3mq.egg-info/requires.txt
web3mq.egg-info/top_level.txt